genro_tytx/__init__.py
genro_tytx/decode.py
genro_tytx/encode.py
genro_tytx/http.py
genro_tytx/msgpack.py
genro_tytx/py.typed
genro_tytx/qs.py
genro_tytx/registry.py
genro_tytx/utils.py
genro_tytx/xml.py
genro_tytx-0.7.4.dist-info/METADATA
genro_tytx-0.7.4.dist-info/WHEEL
genro_tytx-0.7.4.dist-info/RECORD
