Metadata-Version: 2.4
Name: genro-tytx
Version: 0.7.4
Summary: TYTX Base - Typed text protocol for scalar types (JSON/XML/MessagePack)
Project-URL: Homepage, https://github.com/genropy/genro-tytx
Project-URL: Repository, https://github.com/genropy/genro-tytx
Project-URL: Documentation, https://github.com/genropy/genro-tytx#readme
Author-email: Genropy Team <info@genropy.org>
License-Expression: Apache-2.0
Keywords: genropy,json,msgpack,serialization,typed,tytx,xml
Classifier: Development Status :: 4 - Beta
Classifier: Intended Audience :: Developers
Classifier: License :: OSI Approved :: Apache Software License
Classifier: Programming Language :: Python :: 3
Classifier: Programming Language :: Python :: 3.10
Classifier: Programming Language :: Python :: 3.11
Classifier: Programming Language :: Python :: 3.12
Classifier: Topic :: Software Development :: Libraries :: Python Modules
Requires-Python: >=3.10
Provides-Extra: all
Requires-Dist: msgpack>=1.0; extra == 'all'
Requires-Dist: orjson>=3.9; extra == 'all'
Provides-Extra: dev
Requires-Dist: msgpack>=1.0; extra == 'dev'
Requires-Dist: orjson>=3.9; extra == 'dev'
Requires-Dist: pytest-asyncio>=0.23; extra == 'dev'
Requires-Dist: pytest-cov>=4.0; extra == 'dev'
Requires-Dist: pytest>=7.0; extra == 'dev'
Provides-Extra: docs
Requires-Dist: myst-parser>=2.0; extra == 'docs'
Requires-Dist: sphinx-rtd-theme>=2.0; extra == 'docs'
Requires-Dist: sphinx>=7.0; extra == 'docs'
Provides-Extra: fast
Requires-Dist: orjson>=3.9; extra == 'fast'
Provides-Extra: msgpack
Requires-Dist: msgpack>=1.0; extra == 'msgpack'
